rsnapshot_docker_compose_backup/__init__.py
rsnapshot_docker_compose_backup/backup_planer.py
rsnapshot_docker_compose_backup/global_values.py
rsnapshot_docker_compose_backup/utils.py
rsnapshot_docker_compose_backup/config/__init__.py
rsnapshot_docker_compose_backup/config/abstract_config.py
rsnapshot_docker_compose_backup/config/backup.ini
rsnapshot_docker_compose_backup/config/default_config.py
rsnapshot_docker_compose_backup/docker/__init__.py
rsnapshot_docker_compose_backup/docker/docker.py
rsnapshot_docker_compose_backup/docker/docker_compose.py
rsnapshot_docker_compose_backup/structure/__init__.py
rsnapshot_docker_compose_backup/structure/container.py
rsnapshot_docker_compose_backup/structure/project.py
rsnapshot_docker_compose_backup/structure/volume.py
rsnapshot_docker_compose_backup-0.9.12.dist-info/METADATA
rsnapshot_docker_compose_backup-0.9.12.dist-info/WHEEL
rsnapshot_docker_compose_backup-0.9.12.dist-info/entry_points.txt
rsnapshot_docker_compose_backup-0.9.12.dist-info/licenses/LICENSE
rsnapshot_docker_compose_backup-0.9.12.dist-info/RECORD
