Metadata-Version: 2.3
Name: rsnapshot-docker-compose-backup
Version: 0.9.12
Summary: A config generator for rsnapshot
Project-URL: Homepage, https://github.com/d3kad3nt/rsnapshot-docker-compose-backup
Project-URL: Issues, https://github.com/d3kad3nt/rsnapshot-docker-compose-backup/issues
Author-email: Christoph Wildhagen <git@christoph-wildhagen.de>
License-File: LICENSE
Classifier: License :: OSI Approved :: Apache Software License
Classifier: Operating System :: OS Independent
Classifier: Programming Language :: Python :: 3
Requires-Python: >=3.8
